{"cameraMode":{"drawMode":0,"name":"Shaded","section":"Shading Mode"},"sceneLighting":true,"audioPlay":false,"sceneViewState":{"showFog":true,"showMaterialUpdate":false,"showSkybox":true,"showFlares":true,"showImageEffects":true,"showParticleSystems":true},"in2DMode":false,"pivot":{"x":-4.657338619232178,"y":0.12830233573913575,"z":-5.9361443519592289},"rotation":{"x":-0.20974481105804444,"y":0.731843888759613,"z":-0.2580578625202179,"w":-0.5948342680931091},"size":17.445396423339845,"orthographic":false}